mensajes/__init__.py
mensajes/adios/__init__.py
mensajes/adios/despedida.py
mensajes/hola/__init__.py
mensajes/hola/saludos.py
mensajes_jcorredor-6.0.dist-info/licenses/LICENSE
tests/__init__.py
tests/test_hola.py
mensajes_jcorredor-6.0.dist-info/METADATA
mensajes_jcorredor-6.0.dist-info/WHEEL
mensajes_jcorredor-6.0.dist-info/top_level.txt
mensajes_jcorredor-6.0.dist-info/RECORD
